component_registry_bindings/__init__.py
component_registry_bindings/constants.py
component_registry_bindings/exceptions.py
component_registry_bindings/helpers.py
component_registry_bindings/iterators.py
component_registry_bindings/session.py
component_registry_bindings/bindings/__init__.py
component_registry_bindings/bindings/python_client/__init__.py
component_registry_bindings/bindings/python_client/client.py
component_registry_bindings/bindings/python_client/types.py
component_registry_bindings/bindings/python_client/api/__init__.py
component_registry_bindings/bindings/python_client/api/authentication_status/__init__.py
component_registry_bindings/bindings/python_client/api/authentication_status/authentication_status_retrieve.py
component_registry_bindings/bindings/python_client/api/controlled_access_test/__init__.py
component_registry_bindings/bindings/python_client/api/controlled_access_test/controlled_access_test_retrieve.py
component_registry_bindings/bindings/python_client/api/healthy/__init__.py
component_registry_bindings/bindings/python_client/api/healthy/healthy_retrieve.py
component_registry_bindings/bindings/python_client/api/token_auth_test/__init__.py
component_registry_bindings/bindings/python_client/api/token_auth_test/token_auth_test_create.py
component_registry_bindings/bindings/python_client/api/token_auth_test/token_auth_test_retrieve.py
component_registry_bindings/bindings/python_client/api/v1/__init__.py
component_registry_bindings/bindings/python_client/api/v1/v1_builds_list.py
component_registry_bindings/bindings/python_client/api/v1/v1_builds_retrieve.py
component_registry_bindings/bindings/python_client/api/v1/v1_channels_list.py
component_registry_bindings/bindings/python_client/api/v1/v1_channels_retrieve.py
component_registry_bindings/bindings/python_client/api/v1/v1_components_list.py
component_registry_bindings/bindings/python_client/api/v1/v1_components_manifest_retrieve.py
component_registry_bindings-1.4.0.dist-info/LICENSE
component_registry_bindings-1.4.0.dist-info/METADATA
component_registry_bindings-1.4.0.dist-info/WHEEL
component_registry_bindings-1.4.0.dist-info/top_level.txt
component_registry_bindings-1.4.0.dist-info/RECORD
