Metadata-Version: 2.1
Name: component-registry-bindings
Version: 1.4.0
Summary: Python bindings for accessing Component Registry API
Home-page: https://github.com/RedHatProductSecurity/component-registry-bindings
Author: Jakub Frejlach, Red Hat Product Security
Author-email: jfrejlac@redhat.com
Classifier: Programming Language :: Python :: 3
Requires-Python: >=3.6
License-File: LICENSE
Requires-Dist: attrs
Requires-Dist: requests
Requires-Dist: python-dateutil
Requires-Dist: aiohttp
